gesture_control_api/__init__.py
gesture_control_api/cameracontrol.py
gesture_control_api/detector.py
gesture_control_api/gesturecontrolapi.py
gesture_control_api/gesturemodel.py
gesture_control_api/imaging.py
gesture_control_api/landmarking.py
gesture_control_api-0.0.3.dist-info/METADATA
gesture_control_api-0.0.3.dist-info/WHEEL
gesture_control_api-0.0.3.dist-info/top_level.txt
gesture_control_api-0.0.3.dist-info/RECORD
