Metadata-Version: 2.1
Name: gesture-control-api
Version: 0.0.3
Summary: Simple gesture control API for 3D software
Author: Marcell Dancsó
Requires-Dist: absl-py (==1.4.0)
Requires-Dist: astunparse (==1.6.3)
Requires-Dist: attrs (==23.1.0)
Requires-Dist: cachetools (==5.3.0)
Requires-Dist: certifi (==2023.5.7)
Requires-Dist: cffi (==1.15.1)
Requires-Dist: charset-normalizer (==3.1.0)
Requires-Dist: contourpy (==1.0.7)
Requires-Dist: cycler (==0.11.0)
Requires-Dist: flatbuffers (==23.5.9)
Requires-Dist: fonttools (==4.39.4)
Requires-Dist: gast (==0.4.0)
Requires-Dist: google-auth (==2.18.1)
Requires-Dist: google-auth-oauthlib (==1.0.0)
Requires-Dist: google-pasta (==0.2.0)
Requires-Dist: grpcio (==1.54.2)
Requires-Dist: h5py (==3.8.0)
Requires-Dist: idna (==3.4)
Requires-Dist: importlib-metadata (==6.6.0)
Requires-Dist: importlib-resources (==5.12.0)
Requires-Dist: jax (==0.4.10)
Requires-Dist: keras (==2.12.0)
Requires-Dist: kiwisolver (==1.4.4)
Requires-Dist: libclang (==16.0.0)
Requires-Dist: Markdown (==3.4.3)
Requires-Dist: MarkupSafe (==2.1.2)
Requires-Dist: matplotlib (==3.7.1)
Requires-Dist: mediapipe (==0.10.0)
Requires-Dist: ml-dtypes (==0.1.0)
Requires-Dist: numpy (==1.23.5)
Requires-Dist: oauthlib (==3.2.2)
Requires-Dist: opencv-contrib-python (==4.7.0.72)
Requires-Dist: opencv-python (==4.7.0.72)
Requires-Dist: opt-einsum (==3.3.0)
Requires-Dist: packaging (==23.1)
Requires-Dist: Panda3D (==1.10.13)
Requires-Dist: panda3d-simplepbr (==0.10)
Requires-Dist: Pillow (==9.5.0)
Requires-Dist: protobuf (==3.20.3)
Requires-Dist: pyasn1 (==0.5.0)
Requires-Dist: pyasn1-modules (==0.3.0)
Requires-Dist: pycparser (==2.21)
Requires-Dist: pyparsing (==3.0.9)
Requires-Dist: python-dateutil (==2.8.2)
Requires-Dist: requests (==2.31.0)
Requires-Dist: requests-oauthlib (==1.3.1)
Requires-Dist: rsa (==4.9)
Requires-Dist: scipy (==1.10.1)
Requires-Dist: six (==1.16.0)
Requires-Dist: sounddevice (==0.4.6)
Requires-Dist: tensorboard (==2.12.3)
Requires-Dist: tensorboard-data-server (==0.7.0)
Requires-Dist: tensorflow (==2.12.0)
Requires-Dist: tensorflow-estimator (==2.12.0)
Requires-Dist: tensorflow-intel (==2.12.0)
Requires-Dist: tensorflow-io-gcs-filesystem (==0.31.0)
Requires-Dist: termcolor (==2.3.0)
Requires-Dist: typing-extensions (==4.6.2)
Requires-Dist: urllib3 (==1.26.16)
Requires-Dist: Werkzeug (==2.3.4)
Requires-Dist: wrapt (==1.14.1)
Requires-Dist: zipp (==3.15.0)
